{
  "version": "1.0",
  "defaultProvider": "cdnjs",
  "libraries": [
    {
      "library": "bootstrap-datepicker@1.9.0",
      "destination": "wwwroot/lib/bootstrap/dist/",
      "files": [
        "js/bootstrap-datepicker.min.js",
        "css/bootstrap-datepicker3.min.css"
      ]
    },
    {
      "library": "jqueryui@1.12.1",
      "destination": "wwwroot/lib/jqueryui/"
    },
    {
      "library": "twitter-bootstrap@4.4.1",
      "destination": "wwwroot/lib/bootstrap/dist/"
    },
{
  "provider": "jsdelivr",
  "library": "glyphicons@0.2.0",
  "destination": "wwwroot/lib/glyphicons/dist/"
}
]
}